{
  "id": "yuandocs/合规风控/5.2-法务合规/知识产权",
  "title": "知识产权 Intellectual Property",
  "description": "最后更新时间：2024-03-21",
  "source": "@site/docs/yuandocs/5-合规风控/5.2-法务合规/知识产权.md",
  "sourceDirName": "yuandocs/5-合规风控/5.2-法务合规",
  "slug": "/yuandocs/合规风控/5.2-法务合规/知识产权",
  "permalink": "/YuanOversea/docs/yuandocs/合规风控/5.2-法务合规/知识产权",
  "draft": false,
  "unlisted": false,
  "editUrl": "https://github.com/AlbertBouny/YuanOversea/edit/main/docs/yuandocs/5-合规风控/5.2-法务合规/知识产权.md",
  "tags": [],
  "version": "current",
  "frontMatter": {}
}