{
  "id": "yuandocs/核心业务/1.1-平台运营/其他平台/Lazada/平台介绍",
  "title": "Lazada平台介绍 Platform Introduction",
  "description": "最后更新时间：2024-03-21",
  "source": "@site/docs/yuandocs/1-核心业务/1.1-平台运营/其他平台/Lazada/平台介绍.md",
  "sourceDirName": "yuandocs/1-核心业务/1.1-平台运营/其他平台/Lazada",
  "slug": "/yuandocs/核心业务/1.1-平台运营/其他平台/Lazada/平台介绍",
  "permalink": "/YuanOversea/docs/yuandocs/核心业务/1.1-平台运营/其他平台/Lazada/平台介绍",
  "draft": false,
  "unlisted": false,
  "editUrl": "https://github.com/AlbertBouny/YuanOversea/edit/main/docs/yuandocs/1-核心业务/1.1-平台运营/其他平台/Lazada/平台介绍.md",
  "tags": [],
  "version": "current",
  "frontMatter": {}
}