{
  "id": "compliance/5.1-平台合规/账号安全",
  "title": "账号安全 Account Security",
  "description": "最后更新时间：2024-03-21",
  "source": "@site/docs/compliance/5.1-平台合规/账号安全.md",
  "sourceDirName": "compliance/5.1-平台合规",
  "slug": "/compliance/5.1-平台合规/账号安全",
  "permalink": "/YuanOversea/docs/compliance/5.1-平台合规/账号安全",
  "draft": false,
  "unlisted": false,
  "editUrl": "https://github.com/your-org/kuajingdianshang/tree/main/docs/compliance/5.1-平台合规/账号安全.md",
  "tags": [],
  "version": "current",
  "frontMatter": {}
}